logaware/__init__.py
logaware/logger.py
logaware/metalogger.py
logaware-0.2.0.dist-info/DESCRIPTION.rst
logaware-0.2.0.dist-info/METADATA
logaware-0.2.0.dist-info/RECORD
logaware-0.2.0.dist-info/WHEEL
logaware-0.2.0.dist-info/metadata.json
logaware-0.2.0.dist-info/top_level.txt
